<?xml version="1.0" encoding="utf-8" ?><dwsync><file name="AVAILABLE_APPLICATIONS_CACHE_en_Crystal" server="us20.siteground.us" local="3611357332" remote="3611353500" Dst="-1" /><file name="all_iplist.db" server="us20.siteground.us" local="3611357332" remote="3611353500" Dst="-1" /><file name="ftp_LISTSTORE" server="us20.siteground.us" local="3611357332" remote="3611353500" Dst="-1" /><file name="mysql-db-count" server="us20.siteground.us" local="3611357333" remote="3611353500" Dst="-1" /><file name="postgres-db-count" server="us20.siteground.us" local="3611357333" remote="3611353500" Dst="-1" /><file name="MOUNTS_CACHE__proc_mounts" server="us20.siteground.us" local="3611357333" remote="3611353500" Dst="-1" /><file name="all_iplist.db" server="us20.siteground.us//public_html/" local="3611357332" remote="3611354400" Dst="-1" /><file name="AVAILABLE_APPLICATIONS_CACHE_en_Crystal" server="us20.siteground.us//public_html/" local="3611357332" remote="3611354400" Dst="-1" /><file name="ftp_LISTSTORE" server="us20.siteground.us//public_html/" local="3611357332" remote="3611354400" Dst="-1" /><file name="MOUNTS_CACHE__proc_mounts" server="us20.siteground.us//public_html/" local="3611357333" remote="3611354400" Dst="-1" /><file name="mysql-db-count" server="us20.siteground.us//public_html/" local="3611357333" remote="3611354400" Dst="-1" /><file name="postgres-db-count" server="us20.siteground.us//public_html/" local="3611357333" remote="3611354400" Dst="-1" /><file name="Quota.pm__saranshg" server="us20.siteground.us//public_html/" local="3611357332" remote="3611354400" Dst="-1" /></dwsync>